{"ctfname": "starctf19", "challenges": [{"name": "babyflash", "solver": ["UnblvR"], "solve_date": 1556394586, "category": "misc"}, {"name": "babyprng", "solver": ["slicklibro"], "solve_date": 1556366674, "category": "crypto"}, {"name": "babyshell", "solver": ["kileak"], "solve_date": 1556447828, "category": "pwn"}, {"name": "blindpwn", "solver": ["kileak"], "solve_date": 1556359687, "category": "pwn"}, {"name": "checkin", "solver": ["slicklibro"], "solve_date": 1556340866, "category": "misc"}, {"name": "girlfriend", "solver": ["kileak"], "solve_date": 1556350600, "category": "pwn"}, {"name": "hack_me", "solver": ["kileak"], "solve_date": 1556446207, "category": "pwn"}, {"name": "mywebsql", "solver": ["corb3nik"], "solve_date": 1556350286, "category": "web"}, {"name": "otaku", "solver": ["UnblvR"], "solve_date": 1556412332, "category": "misc"}, {"name": "quicksort", "solver": ["kileak"], "solve_date": 1556362768, "category": "pwn"}, {"name": "sokoban", "solver": ["UnblvR"], "solve_date": 1556459697, "category": "misc"}, {"name": "upxofcpp", "solver": ["kileak"], "solve_date": 1556451744, "category": "pwn"}]}