{"ctfname": "tamuctf20", "challenges": [{"name": "652ahs", "solver": ["mementomori"], "solve_date": 1584743286, "category": "crypto"}, {"name": "about_time", "solver": ["mementomori"], "solve_date": 1584747689, "category": "re"}, {"name": "alcapone", "solver": ["mementomori"], "solve_date": 1584727394, "category": "misc"}, {"name": "angr", "solver": ["mementomori"], "solve_date": 1584677267, "category": "re"}, {"name": "b64decoder", "solver": ["crclark"], "solve_date": 1584672205, "category": "pwn"}, {"name": "bbpwn", "solver": ["mementomori"], "solve_date": 1584671672, "category": "pwn"}, {"name": "blind", "solver": ["mementomori"], "solve_date": 1584671152, "category": "misc"}, {"name": "calculataser", "solver": ["mementomori"], "solve_date": 1584802612, "category": "pwn"}, {"name": "corrupted_disk", "solver": ["whoami"], "solve_date": 1584669076, "category": "misc"}, {"name": "credits", "solver": ["mementomori"], "solve_date": 1584666537, "category": "web"}, {"name": "echo", "solver": ["mementomori"], "solve_date": 1584672139, "category": "pwn"}, {"name": "eternal_game", "solver": ["mementomori", "apoq0x80"], "solve_date": 1584723351, "category": "crypto"}, {"name": "filestorage", "solver": ["mementomori"], "solve_date": 1584666270, "category": "web"}, {"name": "geography", "solver": ["mementomori", "whoami"], "solve_date": 1584726875, "category": "misc"}, {"name": "getting_confused", "solver": ["mementomori"], "solve_date": 1584748610, "category": "pwn"}, {"name": "gunzip", "solver": ["mementomori"], "solve_date": 1584673684, "category": "pw"}, {"name": "helpful_builder", "solver": ["luter14", "circleous"], "solve_date": 1585065394, "category": "net"}, {"name": "instagram", "solver": ["mementomori"], "solve_date": 1584671518, "category": "misc"}, {"name": "just_bc", "solver": ["circleous"], "solve_date": 1584786450, "category": "rev"}, {"name": "leaning-tower", "solver": ["mementomori", "towel"], "solve_date": 1585040238, "category": "crypto"}, {"name": "lejit", "solver": ["circleous"], "solve_date": 1584792672, "category": "pwn"}, {"name": "listen", "solver": ["whoami"], "solve_date": 1584670207, "category": "network"}, {"name": "mentalmath", "solver": ["sapra"], "solve_date": 1584692668, "category": "web"}, {"name": "morecredits", "solver": ["mementomori"], "solve_date": 1584668036, "category": "web"}, {"name": "morecredits2", "solver": ["ysf"], "solve_date": 1584735016, "category": "web"}, {"name": "my_first_blog", "solver": ["mementomori"], "solve_date": 1584703239, "category": "net"}, {"name": "not_so_great", "solver": ["mementomori", "madness"], "solve_date": 1584682582, "category": "misc"}, {"name": "obituary_1", "solver": ["whoami"], "solve_date": 1584939999, "category": "net"}, {"name": "obituary_2", "solver": ["circleous", "whoami"], "solve_date": 1584940801, "category": "net"}, {"name": "password", "solver": ["circleous", "luter14", "whoami"], "solve_date": 1585116234, "category": "net"}, {"name": "password-extract", "solver": ["mementomori"], "solve_date": 1584670970, "category": "web"}, {"name": "rsapwn", "solver": ["Noob101"], "solve_date": 1584677102, "category": "misc"}, {"name": "russian_nesting_doll", "solver": ["madness"], "solve_date": 1584672881, "category": "misc"}, {"name": "rusty", "solver": ["mementomori"], "solve_date": 1584672528, "category": "re"}, {"name": "sigma", "solver": ["whoami", "apoq0x80"], "solve_date": 1584718983, "category": "crypto"}, {"name": "spell_icups", "solver": ["luter14"], "solve_date": 1585134204, "category": "net"}, {"name": "splattercalc", "solver": ["circleous"], "solve_date": 1584791135, "category": "rev"}, {"name": "toc_to_who", "solver": ["circleous"], "solve_date": 1585008041, "category": "pwn"}, {"name": "toomany1", "solver": ["mementomori"], "solve_date": 1584668605, "category": "web"}, {"name": "troll", "solver": ["mementomori"], "solve_date": 1584679538, "category": "pwn"}, {"name": "vault", "solver": ["mementomori"], "solve_date": 1584664357, "category": "re"}, {"name": "woof_woof", "solver": ["whoami"], "solve_date": 1584719319, "category": "misc"}]}