{"challenges": [{"solve_date": 1523661823, "name": "bitpuzzle", "solver": ["arxenix"], "category": "misc"}, {"solve_date": 1523655576, "name": "breakout", "solver": ["kileak"], "category": "pwn"}, {"solve_date": 1523650769, "name": "ezpz", "solver": ["kileak"], "category": "pwn"}, {"solve_date": 1523652285, "name": "forker1", "solver": ["kileak"], "category": "pwn"}, {"solve_date": 1523657607, "name": "forker2", "solver": ["kileak"], "category": "pwn"}, {"solve_date": 1523659612, "name": "forker3", "solver": ["kileak"], "category": "pwn"}, {"solve_date": 1523658133, "name": "guess5", "solver": ["arxenix"], "category": "crypto"}, {"solve_date": 1523661089, "name": "penguin", "solver": ["kileak"], "category": "re"}, {"solve_date": 1523650950, "name": "shelljail1", "solver": ["kileak"], "category": "pwn"}, {"solve_date": 1523660081, "name": "shelljail2", "solver": ["kileak"], "category": "pwn"}, {"solve_date": 1523681796, "name": "vault", "solver": ["vakzz"], "category": "web"}], "ctfname": "wpictf18"}